.gitattributes
.gitignore
.pre-commit-config.yaml
.pylintrc
.readthedocs.yml
ACKNOWLEDGMENT.md
AUTHORS.txt
CHANGELOG.rst
CONTRIBUTING.md
COPYING
COPYING.LESSER
MANIFEST.in
README.rst
setup.py
tox.ini
.github/pull_request_template.md
.github/workflows/publish-sdist.yml
.github/workflows/run-tox.yml
doc/Makefile
doc/source/api.rst
doc/source/changelog.rst
doc/source/conf.py
doc/source/index.rst
doc/source/morphdb.rst
doc/source/simplify.rst
doc/source/logo/BBP-Morph-Tool.jpg
doc/source/static/simplify-diff.gif
doc/source/static/simplify-diff.png
examples/dendrogram.py
examples/dendrogram_plain_example.swc
examples/draw_morphology.py
functional_tests/Neuron.swc
functional_tests/circle_contour.asc
functional_tests/circle_contour.h5
functional_tests/circle_contour.swc
functional_tests/morphio.swc
functional_tests/real_neuron.asc
functional_tests/real_neuron2.asc
functional_tests/simple.asc
functional_tests/single-point-soma.swc
functional_tests/soma_three_points_cylinder.swc
functional_tests/test_converter.py
functional_tests/test_nrnhines_mapper.py
morph_tool/__init__.py
morph_tool/amira_converter.py
morph_tool/apical_point.py
morph_tool/axon_point.py
morph_tool/cli.py
morph_tool/converter.py
morph_tool/exceptions.py
morph_tool/graft.py
morph_tool/loader.py
morph_tool/morphdb.py
morph_tool/morphio_diff.py
morph_tool/neuron_surface.py
morph_tool/nrnhines.py
morph_tool/resampling.py
morph_tool/simplify.py
morph_tool/spatial.py
morph_tool/transform.py
morph_tool/utils.py
morph_tool.egg-info/PKG-INFO
morph_tool.egg-info/SOURCES.txt
morph_tool.egg-info/dependency_links.txt
morph_tool.egg-info/entry_points.txt
morph_tool.egg-info/requires.txt
morph_tool.egg-info/top_level.txt
morph_tool/plot/__init__.py
morph_tool/plot/consts.py
morph_tool/plot/dendrogram.py
morph_tool/plot/morphology.py
tests/test_amira_converter.py
tests/test_apical_point.py
tests/test_axon_point.py
tests/test_cli.py
tests/test_converter.py
tests/test_dendrogram.py
tests/test_diff.py
tests/test_graft.py
tests/test_loader.py
tests/test_morphdb.py
tests/test_nrnhines.py
tests/test_resampling.py
tests/test_simplify.py
tests/test_spatial.py
tests/test_transform.py
tests/test_utils.py
tests/data/amira_cell.am
