Metadata-Version: 2.1
Name: morph-tool
Version: 2.10.2
Summary: A collection of CLIs and python function related to morphology handling
Home-page: https://github.com/bluebrain/morph-tool
Author: Blue Brain Project, EPFL
License: LGPLv3
Classifier: Development Status :: 5 - Production/Stable
Classifier: Programming Language :: Python
Classifier: Programming Language :: Python :: 3
Classifier: Programming Language :: Python :: 3.8
Classifier: Programming Language :: Python :: 3.9
Classifier: Programming Language :: Python :: 3.10
Classifier: Programming Language :: Python :: 3.11
Requires-Python: >=3.8
Provides-Extra: nrn
Provides-Extra: parallel
Provides-Extra: plot
Provides-Extra: all
Provides-Extra: docs
License-File: COPYING
License-File: COPYING.LESSER
License-File: AUTHORS.txt
